{
    "id": 8,
    "is_operational": true,
    "icon_code": "f1c0",
    "docker_privileged": false,
    "docker_image": "10.4.4.10:5000/ls8-ortho:2.1.9",
    "priority": 1,
    "timeout": 30,
    "max_tries": 3,
    "manifest": {
        "job": {
            "name": "landsat8-ortho",
            "jobVersion": "2.0",
            "packageVersion": "",
            "title": "Landsat 8 Ortho (OSSIM)",
            "description": "OSSIM is a powerful suite of geospatial libraries and applications used to process imagery, maps, terrain, and vector data. The software has been under active development since 1996 and is deployed across a number of private, federal and civilian agencies.",
            "maintainer": {
                "name": "Radiant Blue",
                "email": ""
            },
            "timeout": 0,
            "interface": {
                "command": "./ls8_ortho.py",
                "inputs": {},
                "outputs": {},
                "settings": []
            }
        },
        "seedVersion": "1.0"
    },
    "job_counts_6h": [
        {
            "status": "QUEUED",
            "count": 3,
            "most_recent": "2015-09-16T18:36:12.278Z",
            "category": null
        }
    ],
    "job_counts_12h": [
        {
            "status": "QUEUED",
            "count": 3,
            "most_recent": "2015-09-16T18:36:12.278Z",
            "category": null
        },
        {
            "status": "COMPLETED",
            "count": 225,
            "most_recent": "2015-09-16T18:36:12.278Z",
            "category": null
        }
    ],
    "job_counts_24h": [
        {
            "status": "QUEUED",
            "count": 3,
            "most_recent": "2015-09-16T18:36:12.278Z",
            "category": null
        },
        {
            "status": "COMPLETED",
            "count": 419,
            "most_recent": "2015-09-16T18:36:12.278Z",
            "category": null
        },
        {
            "status": "FAILED",
            "count": 89,
            "most_recent": "2015-09-16T18:36:12.278Z",
            "category": "SYSTEM"
        }
    ]
}
